youtube_chat_cli/__init__.py
youtube_chat_cli/cli/__init__.py
youtube_chat_cli/cli/main.py
youtube_chat_cli/core/__init__.py
youtube_chat_cli/core/config.py
youtube_chat_cli/core/database.py
youtube_chat_cli/core/youtube_api.py
youtube_chat_cli/models/__init__.py
youtube_chat_cli/services/__init__.py
youtube_chat_cli/services/blueprint/__init__.py
youtube_chat_cli/services/blueprint/generator.py
youtube_chat_cli/services/chat/__init__.py
youtube_chat_cli/services/chat/interface.py
youtube_chat_cli/services/content/__init__.py
youtube_chat_cli/services/content/source_manager.py
youtube_chat_cli/services/import_service/__init__.py
youtube_chat_cli/services/import_service/bulk_import.py
youtube_chat_cli/services/monitoring/__init__.py
youtube_chat_cli/services/monitoring/background_service.py
youtube_chat_cli/services/monitoring/channel_monitor.py
youtube_chat_cli/services/monitoring/video_processor.py
youtube_chat_cli/services/monitoring/video_queue.py
youtube_chat_cli/services/n8n/__init__.py
youtube_chat_cli/services/n8n/client.py
youtube_chat_cli/services/podcast/__init__.py
youtube_chat_cli/services/podcast/generator.py
youtube_chat_cli/services/podcast/styles.py
youtube_chat_cli/services/transcription/__init__.py
youtube_chat_cli/services/transcription/processor.py
youtube_chat_cli/services/tts/__init__.py
youtube_chat_cli/services/tts/config_manager.py
youtube_chat_cli/services/tts/service.py
youtube_chat_cli/services/workflow/__init__.py
youtube_chat_cli/services/workflow/manager.py
youtube_chat_cli/utils/__init__.py
youtube_chat_cli/utils/helpers.py
youtube_chat_cli/utils/llm_service.py
youtube_chat_cli/utils/session_manager.py
youtube_chat_cli-2.1.0.dist-info/LICENSE
youtube_chat_cli-2.1.0.dist-info/METADATA
youtube_chat_cli-2.1.0.dist-info/WHEEL
youtube_chat_cli-2.1.0.dist-info/entry_points.txt
youtube_chat_cli-2.1.0.dist-info/top_level.txt
youtube_chat_cli-2.1.0.dist-info/RECORD
