Metadata-Version: 2.1
Name: youtube-chat-cli
Version: 2.1.0
Summary: AI-powered CLI tool for YouTube video analysis, channel monitoring, and automated content processing
Home-page: https://github.com/usemanusai/youtube-free-deep-research-cli
Author: YouTube Chat CLI Team
Author-email: use.manus.ai@gmail.com
License: MIT
Project-URL: Bug Reports, https://github.com/usemanusai/youtube-free-deep-research-cli/issues
Project-URL: Source, https://github.com/usemanusai/youtube-free-deep-research-cli
Project-URL: Documentation, https://github.com/usemanusai/youtube-free-deep-research-cli#readme
Keywords: cli,ai,youtube,channel-monitoring,tts,transcription,n8n,rag,automation
Platform: any
Classifier: Development Status :: 4 - Beta
Classifier: Intended Audience :: End Users/Desktop
Classifier: License :: OSI Approved :: MIT License
Classifier: Programming Language :: Python :: 3
Classifier: Programming Language :: Python :: 3.8
Classifier: Programming Language :: Python :: 3.9
Classifier: Programming Language :: Python :: 3.10
Classifier: Programming Language :: Python :: 3.11
Classifier: Programming Language :: Python :: 3.12
Classifier: Operating System :: OS Independent
Classifier: Topic :: Internet :: WWW/HTTP
Classifier: Topic :: Scientific/Engineering :: Artificial Intelligence
Classifier: Topic :: Multimedia :: Sound/Audio :: Speech
Classifier: Topic :: Communications :: Chat
Classifier: Topic :: System :: Monitoring
Requires-Python: >=3.8, <4
License-File: LICENSE
Requires-Dist: Pillow (>=9.0.0)
Requires-Dist: PyPDF2 (>=3.0.0)
Requires-Dist: apscheduler (>=3.10.0)
Requires-Dist: beautifulsoup4
Requires-Dist: click
Requires-Dist: colorama
Requires-Dist: deepmultilingualpunctuation
Requires-Dist: edge-tts
Requires-Dist: google-api-python-client (>=2.0.0)
Requires-Dist: google-auth-httplib2 (>=0.2.0)
Requires-Dist: google-auth-oauthlib (>=1.0.0)
Requires-Dist: gtts (>=2.5.0)
Requires-Dist: halo
Requires-Dist: langchain-huggingface
Requires-Dist: langchain-openai
Requires-Dist: moviepy (>=1.0.3)
Requires-Dist: openpyxl (>=3.1.0)
Requires-Dist: pandas (>=1.5.0)
Requires-Dist: pydub (>=0.25.0)
Requires-Dist: pytesseract (>=0.3.10)
Requires-Dist: pytest
Requires-Dist: python-dateutil (>=2.8.0)
Requires-Dist: python-docx (>=0.8.11)
Requires-Dist: python-dotenv
Requires-Dist: requests
Requires-Dist: rich (>=13.0.0)
Requires-Dist: speechrecognition (>=3.10.0)
Requires-Dist: tqdm (>=4.62.0)
Requires-Dist: youtube-transcript-api
Provides-Extra: all
Requires-Dist: black (>=22.0.0) ; extra == 'all'
Requires-Dist: edge-tts (>=6.1.0) ; extra == 'all'
Requires-Dist: flake8 (>=5.0.0) ; extra == 'all'
Requires-Dist: gtts (>=2.3.0) ; extra == 'all'
Requires-Dist: mypy (>=1.0.0) ; extra == 'all'
Requires-Dist: pytest-cov (>=4.0.0) ; extra == 'all'
Requires-Dist: pytest-mock (>=3.0.0) ; extra == 'all'
Requires-Dist: pytest (>=7.0.0) ; extra == 'all'
Requires-Dist: torch (>=2.0.0) ; extra == 'all'
Requires-Dist: torchaudio (>=2.0.0) ; extra == 'all'
Provides-Extra: dev
Requires-Dist: black (>=22.0.0) ; extra == 'dev'
Requires-Dist: flake8 (>=5.0.0) ; extra == 'dev'
Requires-Dist: mypy (>=1.0.0) ; extra == 'dev'
Requires-Dist: pytest-cov (>=4.0.0) ; extra == 'dev'
Requires-Dist: pytest-mock (>=3.0.0) ; extra == 'dev'
Requires-Dist: pytest (>=7.0.0) ; extra == 'dev'
Provides-Extra: tts
Requires-Dist: edge-tts (>=6.1.0) ; extra == 'tts'
Requires-Dist: gtts (>=2.3.0) ; extra == 'tts'
Requires-Dist: torch (>=2.0.0) ; extra == 'tts'
Requires-Dist: torchaudio (>=2.0.0) ; extra == 'tts'
